<?xml version="1.0" ?>
<SmellBaseline>
  <ManuallySuppressedIssues/>
  <CurrentIssues>
    <ID>MaxLineLength:OkHttpInstrumentation.kt$OkHttpInstrumentation$ and the </ID>
    <ID>MaxLineLength:OkHttpInstrumentation.kt$OkHttpInstrumentation$*</ID>
    <ID>MaxLineLength:OkHttpInstrumentation.kt$OkHttpInstrumentation$.</ID>
    <ID>PackageNaming:OkHttp3Singletons.kt$package io.opentelemetry.instrumentation.library.okhttp.v3_0.internal</ID>
    <ID>PackageNaming:OkHttpCallbackAdviceHelper.kt$package io.opentelemetry.instrumentation.library.okhttp.v3_0.internal</ID>
    <ID>PackageNaming:OkHttpInstrumentation.kt$package io.opentelemetry.instrumentation.library.okhttp.v3_0</ID>
    <ID>PackageNaming:TracingCallback.kt$package io.opentelemetry.instrumentation.library.okhttp.v3_0.internal</ID>
  </CurrentIssues>
</SmellBaseline>
